flask_fure/__init__.py
Flask_Fure-0.1.0.dist-info/LICENSE
Flask_Fure-0.1.0.dist-info/METADATA
Flask_Fure-0.1.0.dist-info/WHEEL
Flask_Fure-0.1.0.dist-info/top_level.txt
Flask_Fure-0.1.0.dist-info/RECORD
